{
  "posts": [
    {
      "id": 1,
      "title": "json-server",
      "author": "typicode"
    },
    {
      "id": 2,
      "title": "api development",
      "author": "future technologies"
    },
    {
      "id": 3,
      "title": "frontend frameworks",
      "author": "creative solutions"
    },
    {
      "id": 4,
      "title": "backend integration",
      "author": "global systems"
    },
    {
      "id": 5,
      "title": "database management",
      "author": "data masters"
    },
    {
      "id": 6,
      "title": "version control",
      "author": "code keepers"
    },
    {
      "id": 7,
      "title": "testing strategies",
      "author": "quality assurance inc."
    },
    {
      "id": 8,
      "title": "deployment techniques",
      "author": "deployment experts"
    },
    {
      "id": 9,
      "title": "devops practices",
      "author": "agile works"
    },
    {
      "id": 10,
      "title": "agile methodologies",
      "author": "efficiency group"
    }
  ],
  "comments": [
    {
      "id": 1,
      "body": "some comment",
      "postid": 1
    },
    {
      "id": 2,
      "body": "interesting post",
      "postid": 2
    },
    {
      "id": 3,
      "body": "great insights",
      "postid": 3
    },
    {
      "id": 4,
      "body": "need more examples",
      "postid": 4
    },
    {
      "id": 5,
      "body": "very helpful",
      "postid": 5
    },
    {
      "id": 6,
      "body": "good read",
      "postid": 6
    },
    {
      "id": 7,
      "body": "i disagree",
      "postid": 7
    },
    {
      "id": 8,
      "body": "let's discuss further",
      "postid": 8
    },
    {
      "id": 9,
      "body": "well explained",
      "postid": 9
    },
    {
      "id": 10,
      "body": "thanks for sharing",
      "postid": 10
    }
  ],
  "profile": {
    "name": "typicode"
  },
  "guestbook": [
    {
      "id": 1,
      "name": "Alice",
      "email": "alice1234@mail.com",
      "message": "This is a great website! Love the design."
    },
    {
      "id": 2,
      "name": "Bob",
      "email": "bob_the_builder@mail.net",
      "message": "Had a wonderful experience here. Thank you!"
    },
    {
      "id": 3,
      "name": "Charlie",
      "email": "charlie2024@service.com",
      "message": "I found this site very helpful. Keep up the good work!"
    },
    {
      "id": 4,
      "name": "Diana",
      "email": "diana.loves.code@webmail.org",
      "message": "Amazing content! I will definitely share this with my friends."
    },
    {
      "id": 5,
      "name": "Ethan",
      "email": "ethan_smith78@mail.com",
      "message": "The best site I’ve visited this month!"
    },
    {
      "id": 6,
      "name": "Fiona",
      "email": "fiona.lee89@mail.net",
      "message": "Really enjoyed the articles. Looking forward to more."
    },
    {
      "id": 7,
      "name": "George",
      "email": "george123@inbox.com",
      "message": "Very informative and easy to navigate. Great job!"
    },
    {
      "id": 8,
      "name": "Hannah",
      "email": "hannah.brown@mail.org",
      "message": "I love the layout! So clean and modern."
    },
    {
      "id": 9,
      "name": "Ian",
      "email": "ian_smith45@provider.com",
      "message": "Fantastic resource! Thank you for your hard work."
    },
    {
      "id": 10,
      "name": "Julia",
      "email": "julia_2024@domain.com",
      "message": "I enjoyed reading the posts. Can't wait for the next update!"
    }
  ],
  "todos": [
    {
      "id": 1,
      "task": "laundry",
      "category": "household",
      "priority": "high",
      "startTimeStamp": "2024-10-19T09:00:00Z",
      "endTimeStamp": "2024-10-19T11:00:00Z",
      "memo": "wash black clothes and white clothes separately"
    },
    {
      "id": 2,
      "task": "grocery shopping",
      "category": "household",
      "priority": "medium",
      "startTimeStamp": "2024-10-20T14:00:00Z",
      "endTimeStamp": "2024-10-20T16:00:00Z",
      "memo": "buy vegetables, milk, and eggs"
    },
    {
      "id": 3,
      "task": "submit project report",
      "category": "work",
      "priority": "high",
      "startTimeStamp": "2024-10-21T09:00:00Z",
      "endTimeStamp": "2024-10-21T12:00:00Z",
      "memo": "finalize and submit the Q4 project report"
    },
    {
      "id": 4,
      "task": "doctor appointment",
      "category": "health",
      "priority": "high",
      "startTimeStamp": "2024-10-22T10:00:00Z",
      "endTimeStamp": "2024-10-22T11:00:00Z",
      "memo": "annual health check-up"
    },
    {
      "id": 5,
      "task": "yoga class",
      "category": "fitness",
      "priority": "medium",
      "startTimeStamp": "2024-10-23T18:00:00Z",
      "endTimeStamp": "2024-10-23T19:00:00Z",
      "memo": "bring a yoga mat and water bottle"
    },
    {
      "id": 6,
      "task": "car maintenance",
      "category": "maintenance",
      "priority": "medium",
      "startTimeStamp": "2024-10-24T08:00:00Z",
      "endTimeStamp": "2024-10-24T10:00:00Z",
      "memo": "oil change and tire rotation"
    },
    {
      "id": 7,
      "task": "team meeting",
      "category": "work",
      "priority": "high",
      "startTimeStamp": "2024-10-25T15:00:00Z",
      "endTimeStamp": "2024-10-25T16:30:00Z",
      "memo": "discuss project milestones and deadlines"
    },
    {
      "id": 8,
      "task": "dentist appointment",
      "category": "health",
      "priority": "high",
      "startTimeStamp": "2024-10-26T11:00:00Z",
      "endTimeStamp": "2024-10-26T12:00:00Z",
      "memo": "regular dental check-up"
    },
    {
      "id": 9,
      "task": "pay bills",
      "category": "finance",
      "priority": "high",
      "startTimeStamp": "2024-10-27T00:00:00Z",
      "endTimeStamp": "2024-10-27T00:00:00Z",
      "memo": "pay electricity and internet bills"
    },
    {
      "id": 10,
      "task": "friend's birthday party",
      "category": "social",
      "priority": "low",
      "startTimeStamp": "2024-10-28T19:00:00Z",
      "endTimeStamp": "2024-10-28T23:00:00Z",
      "memo": "buy a gift and confirm attendance"
    }
  ]
}
